{
  "attributes": [
    {
      "default": "nil",
      "size": null,
      "type": "uuid",
      "source": "id",
      "references": null,
      "allow_nil?": false,
      "generated?": false,
      "primary_key?": true
    },
    {
      "default": "nil",
      "size": null,
      "type": "text",
      "source": "name",
      "references": null,
      "allow_nil?": false,
      "generated?": false,
      "primary_key?": false
    },
    {
      "default": "nil",
      "size": null,
      "type": "text",
      "source": "description",
      "references": null,
      "allow_nil?": true,
      "generated?": false,
      "primary_key?": false
    },
    {
      "default": "nil",
      "size": null,
      "type": "text",
      "source": "status",
      "references": null,
      "allow_nil?": false,
      "generated?": false,
      "primary_key?": false
    },
    {
      "default": "nil",
      "size": null,
      "type": "map",
      "source": "layout_data",
      "references": null,
      "allow_nil?": true,
      "generated?": false,
      "primary_key?": false
    },
    {
      "default": "nil",
      "size": null,
      "type": "utc_datetime_usec",
      "source": "inserted_at",
      "references": null,
      "allow_nil?": false,
      "generated?": false,
      "primary_key?": false
    },
    {
      "default": "nil",
      "size": null,
      "type": "utc_datetime_usec",
      "source": "updated_at",
      "references": null,
      "allow_nil?": false,
      "generated?": false,
      "primary_key?": false
    }
  ],
  "table": "workflows",
  "hash": "61CBB1E0C6226BDB5707DEBBFAADC891D5798C65CD3A7126BE27C5A2903464A7",
  "repo": "Elixir.Invader.Repo",
  "multitenancy": {
    "global": null,
    "attribute": null,
    "strategy": null
  },
  "identities": [
    {
      "name": "unique_name",
      "keys": [
        "name"
      ],
      "base_filter": null,
      "index_name": "workflows_unique_name_index"
    }
  ],
  "strict?": false,
  "custom_indexes": [],
  "custom_statements": [],
  "base_filter": null,
  "has_create_action": true
}